LICENSE
README.md
setup.py
burmesedate/__init__.py
burmethon.egg-info/PKG-INFO
burmethon.egg-info/SOURCES.txt
burmethon.egg-info/dependency_links.txt
burmethon.egg-info/requires.txt
burmethon.egg-info/top_level.txt
test/test_astro.py
test/test_bur.py
test/test_cy.py
test/test_g2j.py
test/test_gmc.py
test/test_j2b.py
test/test_j2g.py
test/test_t2d.py