Metadata-Version: 2.1
Name: burmethon
Version: 0.0.1
Summary: Burmese Calendar API in Python
Home-page: https://github.com/phothinmg/burmethon
Author: Pho Thin Maung
Author-email: phothinmg@gmail.com
License: Apache-2.0
Project-URL: Source Code, https://github.com/phothinmg/burmethon/tree/main/burmethon
Project-URL: Bug Tracker, https://github.com/phothinmg/burmethon/issues
License-File: LICENSE
Requires-Dist: requests
Provides-Extra: dev
Requires-Dist: pytest; extra == "dev"
Requires-Dist: pylint; extra == "dev"
Requires-Dist: coverage; extra == "dev"
Requires-Dist: black; extra == "dev"
Requires-Dist: genbadge; extra == "dev"
